Tensorplex-0.9.post1.dist-info/METADATA
Tensorplex-0.9.post1.dist-info/RECORD
Tensorplex-0.9.post1.dist-info/WHEEL
Tensorplex-0.9.post1.dist-info/top_level.txt
tensorplex/__init__.py
tensorplex/local_loggerplex.py
tensorplex/local_proxy.py
tensorplex/local_tensorplex.py
tensorplex/logger.py
tensorplex/loggerplex.py
tensorplex/tensorplex.py
tensorplex/utils.py
tensorplex/zmq_queue.py
tensorplex/legacy/__init__.py
tensorplex/legacy/loggerplex.py
tensorplex/legacy/remote_call.py
tensorplex/legacy/tensorplex.py
tensorplex/legacy/tensorplex_pyro.py
