Metadata-Version: 2.1
Name: Tensorplex
Version: 0.9.post1
Summary: Distributed wrapper for Tensorboard
Home-page: http://github.com/SurrealAI/Tensorplex
Author: Jim Fan
License: GPLv3
Keywords: Machine Learning,Distributed Computing
Platform: UNKNOWN
Classifier: Development Status :: 5 - Production/Stable
Classifier: Topic :: Scientific/Engineering :: Artificial Intelligence
Classifier: Environment :: Console
Classifier: Programming Language :: Python :: 3
Requires-Python: >=3.5
